{
    "title": "LTInsider | Ivanka Trump at Lord & Taylor",
    "description": "Ivanka Trump presents her new fragrance at Lord &Taylor in New York.",
    "referenceId": "-N8_jxiZarI",
    "date_created": "1453119513",
    "date_modified": "1453119513",
    "tags": "",
    "sourceId": "4",
    "VIDEO_LENGTH": "SHORT",
    "status": "approved",
    "visibility": "1",
    "VV_VI": null,
    "CVV_VI": null,
    "engagement_score": null,
    "conversion_score": null,
    "id": "25895235",
    "loginId": "1758386",
    "entityType": "1",
    "titleTextEncoded": "LTInsider-Ivanka-Trump-at-Lord-Taylor",
    "category": null,
    "duration": 113,
    "settings": {},
    "asset": {
        "sourceId": 4,
        "videoId": "-N8_jxiZarI",
        "externalId": "-N8_jxiZarI",
        "description": "Ivanka Trump presents her new fragrance at Lord &Taylor in New York.",
        "hookText": "Ivanka Trump presents her new fragrance at Lord &Taylor in New York.",
        "author": "Lord & Taylor",
        "timeCreated": 1392759347,
        "thumbnailUrl": "https:\/\/i.ytimg.com\/vi\/-N8_jxiZarI\/hqdefault.jpg",
        "prettyDuration": "00:01:53",
        "numViews": "11967",
        "mediaDuration": 113,
        "definition": "hd",
        "hdvFlag": 1
    },
    "transcripts": null,
    "metrics_statistics": null,
    "tvp_profiles": null,
    "tvp_profiles_manual": null,
    "tvp_profiles_maxscore": null
}