{
    "title": "Lord & Taylor Freehold Holiday Choir",
    "description": "",
    "referenceId": "nsGxpc0zqAs",
    "date_created": "1453119520",
    "date_modified": "1453119520",
    "tags": "",
    "sourceId": "4",
    "VIDEO_LENGTH": "SHORT",
    "status": "approved",
    "visibility": "1",
    "VV_VI": null,
    "CVV_VI": null,
    "engagement_score": null,
    "conversion_score": null,
    "id": "25895488",
    "loginId": "1758386",
    "entityType": "1",
    "titleTextEncoded": "Lord-Taylor-Freehold-Holiday-Choir",
    "category": null,
    "duration": 116,
    "settings": {},
    "asset": {
        "sourceId": 4,
        "videoId": "nsGxpc0zqAs",
        "externalId": "nsGxpc0zqAs",
        "description": "",
        "hookText": "",
        "author": "LordandTaylorStore",
        "timeCreated": 1290120909,
        "thumbnailUrl": "https:\/\/i.ytimg.com\/vi\/nsGxpc0zqAs\/hqdefault.jpg",
        "prettyDuration": "00:01:56",
        "numViews": "64",
        "mediaDuration": 116,
        "definition": "hd",
        "hdvFlag": 1
    },
    "transcripts": null,
    "metrics_statistics": null,
    "tvp_profiles": null,
    "tvp_profiles_manual": null,
    "tvp_profiles_maxscore": null
}