{
    "title": "Bobbi Brown Pretty Powerful",
    "description": "",
    "referenceId": "7IIcLhdoZto",
    "date_created": "1453119514",
    "date_modified": "1453119514",
    "tags": "",
    "sourceId": "4",
    "VIDEO_LENGTH": "SHORT",
    "status": "approved",
    "visibility": "1",
    "VV_VI": null,
    "CVV_VI": null,
    "engagement_score": null,
    "conversion_score": null,
    "id": "25895291",
    "loginId": "1758386",
    "entityType": "1",
    "titleTextEncoded": "Bobbi-Brown-Pretty-Powerful",
    "category": null,
    "duration": 174,
    "settings": {},
    "asset": {
        "sourceId": 4,
        "videoId": "7IIcLhdoZto",
        "externalId": "7IIcLhdoZto",
        "description": "",
        "hookText": "",
        "author": "LordandTaylorStore",
        "timeCreated": 1357580435,
        "thumbnailUrl": "https:\/\/i.ytimg.com\/vi\/7IIcLhdoZto\/hqdefault.jpg",
        "prettyDuration": "00:02:54",
        "numViews": "107",
        "mediaDuration": 174,
        "definition": "hd",
        "hdvFlag": 1
    },
    "transcripts": null,
    "metrics_statistics": null,
    "tvp_profiles": null,
    "tvp_profiles_manual": null,
    "tvp_profiles_maxscore": null
}