{
    "title": "What's Chic Right Now",
    "description": "",
    "referenceId": "qrCa7nrcfUg",
    "date_created": "1453119519",
    "date_modified": "1453119519",
    "tags": "",
    "sourceId": "4",
    "VIDEO_LENGTH": "SHORT",
    "status": "approved",
    "visibility": "1",
    "VV_VI": null,
    "CVV_VI": null,
    "engagement_score": null,
    "conversion_score": null,
    "id": "25895435",
    "loginId": "1758386",
    "entityType": "1",
    "titleTextEncoded": "What-s-Chic-Right-Now",
    "category": null,
    "duration": 34,
    "settings": {},
    "asset": {
        "sourceId": 4,
        "videoId": "qrCa7nrcfUg",
        "externalId": "qrCa7nrcfUg",
        "description": "",
        "hookText": "",
        "author": "Lord & Taylor",
        "timeCreated": 1347570961,
        "thumbnailUrl": "https:\/\/i.ytimg.com\/vi\/qrCa7nrcfUg\/hqdefault.jpg",
        "prettyDuration": "00:00:34",
        "numViews": "76",
        "mediaDuration": 34,
        "definition": "hd",
        "hdvFlag": 1
    },
    "transcripts": null,
    "metrics_statistics": null,
    "tvp_profiles": null,
    "tvp_profiles_manual": null,
    "tvp_profiles_maxscore": null
}