{
    "title": "Speedo launches LZR RACER",
    "description": "Speedo launches the world's fastest swim suit which has been tested at NASA to prove it's superiority in the pool. The LZR (\"Laser\") RACER suit, tested in wind ...",
    "referenceId": "dvMdqvO3R9g",
    "date_created": "1448394407",
    "date_modified": "1448394563",
    "tags": "",
    "sourceId": "4",
    "VIDEO_LENGTH": "SHORT",
    "status": "approved",
    "visibility": "1",
    "VV_VI": "1",
    "CVV_VI": null,
    "engagement_score": "1",
    "conversion_score": null,
    "id": "7815420",
    "loginId": "1758386",
    "entityType": "1",
    "titleTextEncoded": "Speedo-launches-LZR-RACER",
    "category": null,
    "duration": 150,
    "settings": null,
    "asset": {
        "type": "youtube",
        "author": "TVNEWSRELEASE",
        "hdvFlag": 0,
        "hookText": "Speedo launches the world's fastest swim suit which has been tested at NASA to prove it's superiority in the pool. The LZR (\"Laser\") RACER suit, tested in wind ...",
        "tags": "",
        "thumbnailUrl": "https:\/\/i.ytimg.com\/vi\/dvMdqvO3R9g\/hqdefault.jpg",
        "videoId": "dvMdqvO3R9g",
        "mediaDuration": 150,
        "prettyDuration": "00:02:30"
    },
    "transcripts": null,
    "metrics_statistics": "{\"VV_VI\":{\"lastUpdatedDate\":\"2017-05-24\",\"engagement_score\":{\"lastUpdatedDate\":\"2017-05-25\"}}}",
    "tvp_profiles": null,
    "tvp_profiles_manual": null,
    "tvp_profiles_maxscore": null
}